lambdamoo_db/__init__.py
lambdamoo_db/cli.py
lambdamoo_db/database.py
lambdamoo_db/enums.py
lambdamoo_db/exporter.py
lambdamoo_db/reader.py
lambdamoo_db/templates.py
lambdamoo_db/writer.py
lambdamoo_db-0.1.10.dist-info/METADATA
lambdamoo_db-0.1.10.dist-info/WHEEL
lambdamoo_db-0.1.10.dist-info/entry_points.txt
lambdamoo_db-0.1.10.dist-info/RECORD
