Metadata-Version: 2.1
Name: lambdamoo-db
Version: 0.1.10
Summary: Parser for LambdaMOO databases
License: MIT
Author: Katelyn Gigante
Author-email: clockwork.singularity@gmail.com
Requires-Python: >=3.10,<4.0
Classifier: License :: OSI Approved :: MIT License
Classifier: Programming Language :: Python :: 3
Classifier: Programming Language :: Python :: 3.10
Classifier: Programming Language :: Python :: 3.11
Requires-Dist: attrs (>=22.2.0,<23.0.0)
Requires-Dist: cattrs (>=22.2.0,<23.0.0)
Requires-Dist: click (>=8.1.3,<9.0.0)
Requires-Dist: parse (>=1.19.0,<2.0.0)
